django_hashids/__init__.py
django_hashids/exceptions.py
django_hashids/field.py
django_hashids-0.7.1.dist-info/METADATA
django_hashids-0.7.1.dist-info/WHEEL
django_hashids-0.7.1.dist-info/licenses/LICENSE
django_hashids-0.7.1.dist-info/RECORD
