Metadata-Version: 2.4
Name: django-hashids
Version: 0.7.1
Summary: Non-intrusive hashids library for Django
License: MIT
License-File: LICENSE
Keywords: django,hashids,hashid
Author: Shen Li
Author-email: dustet@gmail.com
Requires-Python: >=3.6.2,<4
Classifier: License :: OSI Approved :: MIT License
Classifier: Programming Language :: Python :: 3
Classifier: Programming Language :: Python :: 3.7
Classifier: Programming Language :: Python :: 3.8
Classifier: Programming Language :: Python :: 3.9
Classifier: Programming Language :: Python :: 3.10
Classifier: Programming Language :: Python :: 3.11
Classifier: Programming Language :: Python :: 3.12
Classifier: Programming Language :: Python :: 3.13
Classifier: Programming Language :: Python :: 3.14
Requires-Dist: hashids (>=1.0.2)
Project-URL: Homepage, https://github.com/ericls/django-hashids
Project-URL: Repository, https://github.com/ericls/django-hashids
